Compiled from "MainEntry.java"
public class MainEntry {
  public MainEntry();
    Code:
       0: aload_0       
       1: invokespecial #1                  // Method java/lang/Object."<init>":()V
       4: return        

  public static void main(java.lang.String[]);
    Code:
       0: new           #2                  // class MammalInt
       3: dup           
       4: invokespecial #3                  // Method MammalInt."<init>":()V
       7: astore_1      
       8: aload_1       
       9: invokevirtual #4                  // Method MammalInt.init:()V
      12: aload_1       
      13: invokevirtual #5                  // Method MammalInt.eat:()V
      16: aload_1       
      17: invokevirtual #6                  // Method MammalInt.travel:()V
      20: aload_1       
      21: new           #7                  // class DocFooter
      24: dup           
      25: invokespecial #8                  // Method DocFooter."<init>":()V
      28: putfield      #9                  // Field MammalInt.DF:LDocFooter;
      31: getstatic     #10                 // Field java/lang/System.out:Ljava/io/PrintStream;
      34: ldc           #11                 // String MainEntry Exits
      36: invokevirtual #12                 // Method java/io/PrintStream.println:(Ljava/lang/String;)V
      39: return        
}
